Workbook

Sheet Assumptions
A1: FreshBrew Franchise Financial Model
A2: Base Case Assumptions
A4: Assumption | B4: Value | C4: Unit | D4: Notes
A5: Initial Investment | B5: 2000000 | C5: ₹ | D5: Illustrative setup investment for one outlet
A6: Base Monthly Revenue | B6: 800000 | C6: ₹ / month | D6: Base-case outlet revenue assumption
A7: Conservative Monthly Revenue | B7: 600000 | C7: ₹ / month | D7: Sensitivity case required by assignment
A8: Optimistic Monthly Revenue | B8: 1000000 | C8: ₹ / month | D8: Sensitivity case required by assignment
A9: COGS % | B9: 0.3 | C9: % of revenue | D9: Illustrative base assumption
A10: Monthly Rent | B10: 100000 | C10: ₹ / month | D10: Fixed operating cost assumption
A11: Monthly Staff Cost | B11: 180000 | C11: ₹ / month | D11: Fixed operating cost assumption
A12: Marketing % | B12: 0.06 | C12: % of revenue | D12: Variable marketing assumption
A13: Monthly Utilities | B13: 30000 | C13: ₹ / month | D13: Electricity, water, internet, etc.
A14: Other Monthly Costs | B14: 40000 | C14: ₹ / month | D14: Maintenance and miscellaneous operating costs
A15: Franchise / Scale100x Assumptions
A16: Franchise Fee | B16: 500000 | C16: ₹ | D16: Illustrative franchise fee
A17: Royalty % | B17: 0.05 | C17: % of revenue | D17: Illustrative royalty assumption
A18: Scale100x Fee per Successful Deal | B18: 50000 | C18: ₹ / deal | D18: Illustrative modelling assumption; not stated as actual company pricing
A19: Revenue Ram-up Assumptions
A20: Monthly Revenue Ramp-up | B20: 50000 | C20: ₹ / month | D20: Monthly increase during initial revenue ramp-up
A21: Scale100x Deal Growth | B21: 1 | C21: Annual growth | D21: Illustrative scenario assumption
A22: Initial Month Revenue | B22: 500000 | C22: ₹ / month | D22: Illustrative starting revenue for a new outlet

Sheet P&L
A1: FreshBrew Year 1 Monthly P&L
A2: Base Case
A4: Particulars | B4: Jan | C4: Feb | D4: Mar | E4: Apr | F4: May | G4: Jun | H4: Jul | I4: Aug | J4: Sep | K4: Oct | L4: Nov | M4: Dec | N4: year 1
A5: Revenue | B5: =MIN(Assumptions!$B$22,Assumptions!$B$6) -> 500000 | C5: =MIN(B5+Assumptions!$B$20,Assumptions!$B$6) -> 550000 | D5: =MIN(C5+Assumptions!$B$20,Assumptions!$B$6) -> 600000 | E5: =MIN(D5+Assumptions!$B$20,Assumptions!$B$6) -> 650000 | F5: =MIN(E5+Assumptions!$B$20,Assumptions!$B$6) -> 700000 | G5: =MIN(F5+Assumptions!$B$20,Assumptions!$B$6) -> 750000 | H5: =MIN(G5+Assumptions!$B$20,Assumptions!$B$6) -> 800000 | I5: =MIN(H5+Assumptions!$B$20,Assumptions!$B$6) -> 800000 | J5: =MIN(I5+Assumptions!$B$20,Assumptions!$B$6) -> 800000 | ... M5: =MIN(L5+Assumptions!$B$20,Assumptions!$B$6) -> 800000 | N5: =SUM(B5:M5) -> 8550000
A6: COGS | B6: =B5*Assumptions!$B$9 -> 150000 | C6: =C5*Assumptions!$B$9 -> 165000 | D6: =D5*Assumptions!$B$9 -> 180000 | E6: =E5*Assumptions!$B$9 -> 195000 | F6: =F5*Assumptions!$B$9 -> 210000 | G6: =G5*Assumptions!$B$9 -> 225000 | H6: =H5*Assumptions!$B$9 -> 240000 | I6: =I5*Assumptions!$B$9 -> 240000 | ... M6: =M5*Assumptions!$B$9 -> 240000 | N6: =SUM(B6:M6) -> 2565000
A7: Gross Profit | B7: =B5-B6 -> 350000 | C7: =C5-C6 -> 385000 | D7: =D5-D6 -> 420000 | E7: =E5-E6 -> 455000 | F7: =F5-F6 -> 490000 | G7: =G5-G6 -> 525000 | H7: =H5-H6 -> 560000 | I7: =I5-I6 -> 560000 | ... M7: =M5-M6 -> 560000 | N7: =SUM(B7:M7) -> 5985000
A9: Operating Expenses
A10: Rent | B10: =Assumptions!$B$10 -> 100000 | C10: =Assumptions!$B$10 -> 100000 | D10: =Assumptions!$B$10 -> 100000 | E10: =Assumptions!$B$10 -> 100000 | F10: =Assumptions!$B$10 -> 100000 | G10: =Assumptions!$B$10 -> 100000 | H10: =Assumptions!$B$10 -> 100000 | I10: =Assumptions!$B$10 -> 100000 | ... M10: =Assumptions!$B$10 -> 100000 | N10: =SUM(B10:M10) -> 1200000
A11: Staff Cost | B11: =Assumptions!$B$11 -> 180000 | C11: =Assumptions!$B$11 -> 180000 | D11: =Assumptions!$B$11 -> 180000 | E11: =Assumptions!$B$11 -> 180000 | F11: =Assumptions!$B$11 -> 180000 | G11: =Assumptions!$B$11 -> 180000 | H11: =Assumptions!$B$11 -> 180000 | I11: =Assumptions!$B$11 -> 180000 | ... M11: =Assumptions!$B$11 -> 180000 | N11: =SUM(B11:M11) -> 2160000
A12: Marketing | B12: =B5*Assumptions!$B$12 -> 30000 | C12: =C5*Assumptions!$B$12 -> 33000 | D12: =D5*Assumptions!$B$12 -> 36000 | E12: =E5*Assumptions!$B$12 -> 39000 | F12: =F5*Assumptions!$B$12 -> 42000 | G12: =G5*Assumptions!$B$12 -> 45000 | H12: =H5*Assumptions!$B$12 -> 48000 | I12: =I5*Assumptions!$B$12 -> 48000 | ... M12: =M5*Assumptions!$B$12 -> 48000 | N12: =SUM(B12:M12) -> 513000
A13: Utilities | B13: =Assumptions!$B$13 -> 30000 | C13: =Assumptions!$B$13 -> 30000 | D13: =Assumptions!$B$13 -> 30000 | E13: =Assumptions!$B$13 -> 30000 | F13: =Assumptions!$B$13 -> 30000 | G13: =Assumptions!$B$13 -> 30000 | H13: =Assumptions!$B$13 -> 30000 | I13: =Assumptions!$B$13 -> 30000 | ... M13: =Assumptions!$B$13 -> 30000 | N13: =SUM(B13:M13) -> 360000
A14: Other Costs | B14: =Assumptions!$B$14 -> 40000 | C14: =Assumptions!$B$14 -> 40000 | D14: =Assumptions!$B$14 -> 40000 | E14: =Assumptions!$B$14 -> 40000 | F14: =Assumptions!$B$14 -> 40000 | G14: =Assumptions!$B$14 -> 40000 | H14: =Assumptions!$B$14 -> 40000 | I14: =Assumptions!$B$14 -> 40000 | ... M14: =Assumptions!$B$14 -> 40000 | N14: =SUM(B14:M14) -> 480000
A15: Royalty | B15: =B5*Assumptions!$B$17 -> 25000 | C15: =C5*Assumptions!$B$17 -> 27500 | D15: =D5*Assumptions!$B$17 -> 30000 | E15: =E5*Assumptions!$B$17 -> 32500 | F15: =F5*Assumptions!$B$17 -> 35000 | G15: =G5*Assumptions!$B$17 -> 37500 | H15: =H5*Assumptions!$B$17 -> 40000 | I15: =I5*Assumptions!$B$17 -> 40000 | ... M15: =M5*Assumptions!$B$17 -> 40000 | N15: =SUM(B15:M15) -> 427500
A17: Total Operating Expenses | B17: =SUM(B10:B15) -> 405000 | C17: =SUM(C10:C15) -> 410500 | D17: =SUM(D10:D15) -> 416000 | E17: =SUM(E10:E15) -> 421500 | F17: =SUM(F10:F15) -> 427000 | G17: =SUM(G10:G15) -> 432500 | H17: =SUM(H10:H15) -> 438000 | I17: =SUM(I10:I15) -> 438000 | ... M17: =SUM(M10:M15) -> 438000 | N17: =SUM(B17:M17) -> 5140500
A19: Operating Profit | B19: =B7-B17 -> -55000 | C19: =C7-C17 -> -25500 | D19: =D7-D17 -> 4000 | E19: =E7-E17 -> 33500 | F19: =F7-F17 -> 63000 | G19: =G7-G17 -> 92500 | H19: =H7-H17 -> 122000 | I19: =I7-I17 -> 122000 | ... M19: =M7-M17 -> 122000 | N19: =SUM(B19:M19) -> 844500

Sheet Payback
A1: FreshBrew Franchise Payback Analysis
A3: Metric | B3: Value
A4: Initial Investment | B4: =Assumptions!$B$5 -> 2000000
A7: Month | B7: Operating Profit | C7: Cumulative Profit | D7: Investment Remaining
A8: Jan | B8: ='P&L'!B19 -> -55000 | C8: =B8 -> -55000 | D8: =$B$4-C8 -> 2055000
A9: Feb | B9: ='P&L'!C19 -> -25500 | C9: =C8+B9 -> -80500 | D9: =$B$4-C9 -> 2080500
A10: Mar | B10: ='P&L'!D19 -> 4000 | C10: =C9+B10 -> -76500 | D10: =$B$4-C10 -> 2076500
A11: Apr | B11: ='P&L'!E19 -> 33500 | C11: =C10+B11 -> -43000 | D11: =$B$4-C11 -> 2043000
A12: May | B12: ='P&L'!F19 -> 63000 | C12: =C11+B12 -> 20000 | D12: =$B$4-C12 -> 1980000
A13: Jun | B13: ='P&L'!G19 -> 92500 | C13: =C12+B13 -> 112500 | D13: =$B$4-C13 -> 1887500
A14: Jul | B14: ='P&L'!H19 -> 122000 | C14: =C13+B14 -> 234500 | D14: =$B$4-C14 -> 1765500
A15: Aug | B15: ='P&L'!I19 -> 122000 | C15: =C14+B15 -> 356500 | D15: =$B$4-C15 -> 1643500
A16: Sep | B16: ='P&L'!J19 -> 122000 | C16: =C15+B16 -> 478500 | D16: =$B$4-C16 -> 1521500
A17: Oct | B17: ='P&L'!K19 -> 122000 | C17: =C16+B17 -> 600500 | D17: =$B$4-C17 -> 1399500
A18: Nov | B18: ='P&L'!L19 -> 122000 | C18: =C17+B18 -> 722500 | D18: =$B$4-C18 -> 1277500
A19: Dec | B19: ='P&L'!M19 -> 122000 | C19: =C18+B19 -> 844500 | D19: =$B$4-C19 -> 1155500

Sheet Scale100x Projection
A1: Scale100x 3-Year Revenue Projection
A2: Illustrative Base Case
A4: Metric | B4: Value | C4: Unit | D4: Notes
A5: Year 1 Successful Franchise Deals | B5: 50 | C5: Deals | D5: Illustrative Assumption
A6: Scale100x Fee per Successful Deal | B6: =Assumptions!$B$18 -> 50000 | C6: ₹ / deal | D6: Linked to Assumptions
A7: Annual Deal Growth | B7: =Assumptions!$B$21 -> 1 | C7: % | D7: Illustrative assumption
A10: Metric | B10: Year 1 | C10: Year 2 | D10: Year 3
A11: Successful Franchise Deals | B11: =B5 -> 50 | C11: =B11*(1+$B$7) -> 100 | D11: =C11*(1+$B$7) -> 200
A12: Scale100x Revenue | B12: =B11*$B$6 -> 2500000 | C12: =C11*$B$6 -> 5000000 | D12: =D11*$B$6 -> 10000000

Sheet Sensitivity
A1: FreshBrew Revenue Sensitivity Analysis
A2: Monthly Revenue Scenarios
A4: Metric | B4: ₹6L Case | C4: ₹8L Case | D4: ₹10L Case
A5: Monthly Revenue | B5: =Assumptions!$B$7 -> 600000 | C5: =Assumptions!$B$6 -> 800000 | D5: =Assumptions!$B$8 -> 1000000
A6: Annual Revenue | B6: =B5*12 -> 7200000 | C6: =C5*12 -> 9600000 | D6: =D5*12 -> 12000000
A7: Annual COGS | B7: =B6*Assumptions!$B$9 -> 2160000 | C7: =C6*Assumptions!$B$9 -> 2880000 | D7: =D6*Assumptions!$B$9 -> 3600000
A8: Annual Gross Profit | B8: =B6-B7 -> 5040000 | C8: =C6-C7 -> 6720000 | D8: =D6-D7 -> 8400000
A9: Annual Marketing | B9: =B6*Assumptions!$B$12 -> 432000 | C9: =C6*Assumptions!$B$12 -> 576000 | D9: =D6*Assumptions!$B$12 -> 720000
A10: Annual Royalty | B10: =B6*Assumptions!$B$17 -> 360000 | C10: =C6*Assumptions!$B$17 -> 480000 | D10: =D6*Assumptions!$B$17 -> 600000
A11: Annual Fixed Costs | B11: =(Assumptions!$B$10+Assumptions!$B$11+Assumptions!$B$13+Assumptions!$B$14)*12 -> 4200000 | C11: =(Assumptions!$B$10+Assumptions!$B$11+Assumptions!$B$13+Assumptions!$B$14)*12 -> 4200000 | D11: =(Assumptions!$B$10+Assumptions!$B$11+Assumptions!$B$13+Assumptions!$B$14)*12 -> 4200000
A12: Annual Operating Profit | B12: =B8-B9-B10-B11 -> 48000 | C12: =C8-C9-C10-C11 -> 1464000 | D12: =D8-D9-D10-D11 -> 2880000
A13: Initial Investment | B13: =Assumptions!$B$5 -> 2000000 | C13: =Assumptions!$B$5 -> 2000000 | D13: =Assumptions!$B$5 -> 2000000
A14: Simple Payback (Years) | B14: =IFERROR(B13/B12,"N/A") -> 41.666667 | C14: =IFERROR(C13/C12,"N/A") -> 1.3661202 | D14: =IFERROR(D13/D12,"N/A") -> 0.69444444

Sheet Franchisee Input
A1: Franchisee Qualification & ROI Tool
A2: Illustrative Franchisee Assessment
A4: Franchisee Information
A5: Available Investment | B5: 2500000
A6: Expected Monthly Revenue | B6: 800000
A7: Location | B7: Mumbai
A8: F&B Experience | B8: 3
A9: Number of Existing Outlets | B9: 0
A10: Funding Required | B10: 0
A13: Financial Assessment
A14: Required Investment | B14: =Assumptions!$B$5 -> 2000000
A15: Investment Gap | B15: =MAX(B14-B5,0) -> 0
A16: Expected Annual Revenue | B16: =B6*12 -> 9600000
A17: Expected Annual Operating Profit | B17: =Sensitivity!C12 -> 1464000
A18: Simple Payback | B18: =IFERROR(B14/B17,"N/A") -> 1.3661202
A19: Financial Status | B19: =IF(B15>0,"NO-GO",IF(B18<=2,"GO","REVIEW")) -> GO
A22: Qualification Checks
A23: Investment Check | B23: =IF(B5>=B14,"PASS","FAIL") -> PASS
A24: Revenue Check | B24: =IF(B6>=Assumptions!$B$6,"PASS","REVIEW") -> PASS
A25: Experience Check | B25: =IF(B8>=2,"PASS","REVIEW") -> PASS
A26: Overall Qualification | B26: =IF(COUNTIF(B23:B25,"FAIL")>0,"NO-GO",IF(COUNTIF(B23:B25,"REVIEW")>0,"REVIEW","GO")) -> GO
A29: Lead Scoring
A30: Factor | B30: Score | C30: Max Score | D30: Reason
A31: Investment Capacity | B31: =IF(B5>=B14,30,0) -> 30 | C31: =30 -> 30 | D31: Available investment vs required investment
A32: Revenue Potential | B32: =IF(B6>=Assumptions!$B$8,30,IF(B6>=Assumptions!$B$6,25,IF(B6>=Assumptions!$B$7,10,0))) -> 25 | C32: =30 -> 30 | D32: Expected monthly revenue vs scenario benchmarks
A33: F&B Experience | B33: =IF(B8>=5,20,IF(B8>=3,15,IF(B8>=1,10,0))) -> 15 | C33: =20 -> 20 | D33: Relevant operating experience
A34: Existing Outlet Experience | B34: =IF(B9>=3,10,IF(B9>=1,7,5)) -> 5 | C34: =10 -> 10 | D34: Existing operating footprint
A35: Funding Requirement | B35: =IF(B10=0,10,IF(B10<=500000,5,0)) -> 10 | C35: =10 -> 10 | D35: Additional funding dependency
A37: Total Lead Score | B37: =SUM(B31:B35) -> 85 | C37: =SUM(C31:C35) -> 100
A38: Lead Priority | B38: =IF(B37>=80,"HIGH",IF(B37>=60,"MEDIUM","LOW")) -> HIGH
A39: Recommended Action | B39: =IF(B37>=80,"Prioritize for sales call",IF(B37>=60,"Schedule qualification call","Nurture / review later")) -> Prioritize for sales call

Sheet Automation Workflow
A1: Scale100x Franchise Lead Automation
A2: AI-enabled Lead Qualification & ROI Workflow
A4: Step | B4: Trigger / Input | C4: Automation | D4: Tool | E4: Output | F4: Human Checkpoint | G4: Time Saved | H4: Risk
A5: 1 | B5: User clicks Meta Ad | C5: Capture lead and start WhatsApp conversation | D5: Meta Ads + WhatsApp | E5: New WhatsApp lead | F5: None | G5: ~2 min/lead | H5: Ad platform or tracking failure
A6: 2 | B6: New WhatsApp conversation | C6: AI greets lead and asks qualification questions | D6: WhatsApp + AI Agent | E6: Structured lead information | F6: Human takeover if AI cannot understand response | G6: ~5 min/lead | H6: AI misunderstanding user response
A7: 3 | B7: Lead answers qualification questions | C7: Extract budget, location, experience and intent | D7: AI | E7: Qualified lead profile | F7: Review unusual or incomplete responses | G7: ~3 min/lead | H7: Incorrect AI classification
A8: 4 | B8: Qualified lead | C8: Create or update lead record | D8: CRM | E8: Centralised lead profile | F8: Sales team can correct lead data | G8: ~3 min/lead | H8: Duplicate or incomplete CRM record
A9: 5 | B9: Lead profile | C9: Calculate lead score and priority | D9: Scoring Logic | E9: High / Medium / Low | F9: Human review for borderline leads | G9: ~5 min/lead | H9: Poor scoring thresholds
A10: 6 | B10: High-intent / high-score lead | C10: Create consultant task and notify | D10: CRM + Email / Slack | E10: Consultant follow-up task | F10: Consultant takes over | G10: ~5 min/lead | H10: Lead notification failure
A11: 7 | B11: Consultant receives qualified lead | C11: Human handles call and closes opportunity | D11: Consultant / CRM | E11: Deal / Next Action | F11: Required | G11: Not automated | H11: Lead may still not convert
A14: Time Saving Estimate
A15: Manual processing time per lead | B15: 15
A16: Automated processing time per lead | B16: 4
A17: Time saved per lead | B17: =B15-B16 -> 11
A18: Illustrative leads per month | B18: 500
A19: Monthly time saved | B19: =B17*B18 -> 5500
A20: Monthly hours saved | B20: =B19/60 -> 91.666667
A22: Key Risk
A23: AI may incorrectly classify an ambiguous or incomplete franchise lead.
A24: Mitigation
A25: High-value or ambiguous leads should be routed to a human consultant for review before being treated as fully qualified.
